{"title":"Shadowcraft","uid":3787529,"size":69250688,"categoryP":"audio","categoryS":"music","magnet":"?xt=urn:btih:0fb956c0b468dbd3caf2cf930696ca81bbb4c05e&amp;dn=Shadowcraft&amp;tr=udp%3A%2F%2Ftracker.openbittorrent.com%3A80&amp;tr=udp%3A%2F%2Fopen.demonii.com%3A1337&amp;tr=udp%3A%2F%2Ftracker.coppersurfer.tk%3A6969&amp;tr=udp%3A%2F%2Fexodus.desync.com%3A6969","seeders":0,"leechers":1,"uploader":"gasgasman","files":13,"time":1188335764,"description":"Shadowcraft","torrent":{"xt":"urn:btih:0fb956c0b468dbd3caf2cf930696ca81bbb4c05e","amp;dn":"Shadowcraft","amp;tr":["udp%3A%2F%2Ftracker.openbittorrent.com%3A80","udp%3A%2F%2Fopen.demonii.com%3A1337","udp%3A%2F%2Ftracker.coppersurfer.tk%3A6969","udp%3A%2F%2Fexodus.desync.com%3A6969"],"infoHash":"0fb956c0b468dbd3caf2cf930696ca81bbb4c05e","infoHashBuffer":{"type":"Buffer","data":[15,185,86,192,180,104,219,211,202,242,207,147,6,150,202,129,187,180,192,94]},"announce":[],"urlList":[]}}