{"title":"Spartacus.Gods.of.the.Arena.Pt.III.720p.HDTV.x264-IMMERSE","uid":6151179,"size":1596471917,"categoryP":"video","categoryS":"hd___tv_shows","magnet":"?xt=urn:btih:203a5aa43858b8fc2fe6225813701ed779e9b1ec&amp;dn=Spartacus.Gods.of.the.Arena.Pt.III.720p.HDTV.x264-IMMERSE&amp;tr=udp%3A%2F%2Ftracker.openbittorrent.com%3A80&amp;tr=udp%3A%2F%2Fopen.demonii.com%3A1337&amp;tr=udp%3A%2F%2Ftracker.coppersurfer.tk%3A6969&amp;tr=udp%3A%2F%2Fexodus.desync.com%3A6969","seeders":0,"leechers":1,"uploader":"SAFCukO09","files":36,"time":1296883974,"description":"[center][img]http://seat42f.com/images/stories/tvshows/Spartacus/Spartacus-Gods-Of-The-Arena-Poster.jpg[/img][/center]\n\n\n[center]\n. ..:: info ::.. .\n\nEpisode.......: Spartacus\nRelease Date..: 2011-02-04\nRelease Size..: 1493.00Mb\nPlay Time.....: 55:53\nResolution....: 1280x720\nVideo bitrate.: 3347kbps\nAudio info....: 6ch, 384kbps\nSubtitles.....: English\n\nnotes ::.. .\n\noPi\n'09","torrent":{"xt":"urn:btih:203a5aa43858b8fc2fe6225813701ed779e9b1ec","amp;dn":"Spartacus.Gods.of.the.Arena.Pt.III.720p.HDTV.x264-IMMERSE","amp;tr":["udp%3A%2F%2Ftracker.openbittorrent.com%3A80","udp%3A%2F%2Fopen.demonii.com%3A1337","udp%3A%2F%2Ftracker.coppersurfer.tk%3A6969","udp%3A%2F%2Fexodus.desync.com%3A6969"],"infoHash":"203a5aa43858b8fc2fe6225813701ed779e9b1ec","infoHashBuffer":{"type":"Buffer","data":[32,58,90,164,56,88,184,252,47,230,34,88,19,112,30,215,121,233,177,236]},"announce":[],"urlList":[]}}