{"title":"7 beastie boys albums by jody!","uid":4780810,"size":385554798,"categoryP":"audio","categoryS":"music","magnet":"?xt=urn:btih:2bd8b4ea48147a848b527435b8a0178c8d8df6c7&amp;dn=7+beastie+boys+albums+by+jody%21&amp;tr=udp%3A%2F%2Ftracker.openbittorrent.com%3A80&amp;tr=udp%3A%2F%2Fopen.demonii.com%3A1337&amp;tr=udp%3A%2F%2Ftracker.coppersurfer.tk%3A6969&amp;tr=udp%3A%2F%2Fexodus.desync.com%3A6969","seeders":0,"leechers":0,"uploader":"jody99","files":106,"time":1237336482,"description":"7 beastie boys albums by jody!","torrent":{"xt":"urn:btih:2bd8b4ea48147a848b527435b8a0178c8d8df6c7","amp;dn":"7+beastie+boys+albums+by+jody%21","amp;tr":["udp%3A%2F%2Ftracker.openbittorrent.com%3A80","udp%3A%2F%2Fopen.demonii.com%3A1337","udp%3A%2F%2Ftracker.coppersurfer.tk%3A6969","udp%3A%2F%2Fexodus.desync.com%3A6969"],"infoHash":"2bd8b4ea48147a848b527435b8a0178c8d8df6c7","infoHashBuffer":{"type":"Buffer","data":[43,216,180,234,72,20,122,132,139,82,116,53,184,160,23,140,141,141,246,199]},"announce":[],"urlList":[]}}