{"title":"How High FULL DVD ISO","uid":3668489,"size":7798460858,"categoryP":"video","categoryS":"movies_dvdr","magnet":"?xt=urn:btih:4aff1f42249b0a4a06c82a87d8790c60310b8f59&amp;dn=How+High+FULL+DVD+ISO&amp;tr=udp%3A%2F%2Ftracker.openbittorrent.com%3A80&amp;tr=udp%3A%2F%2Fopen.demonii.com%3A1337&amp;tr=udp%3A%2F%2Ftracker.coppersurfer.tk%3A6969&amp;tr=udp%3A%2F%2Fexodus.desync.com%3A6969","seeders":0,"leechers":0,"uploader":"supermansaleen","files":-1,"time":1177052851,"description":"Full DVD ISO!\n\nJust use WinRAR or a similar program to extract the ISO and from there, to preview it before you buy it, you can burn to DVD or mount with a program like Alcohol 120% and play with a program such as WinDVD 8.\n\nEnjoy and be sure to help others by seeding it!","torrent":{"xt":"urn:btih:4aff1f42249b0a4a06c82a87d8790c60310b8f59","amp;dn":"How+High+FULL+DVD+ISO","amp;tr":["udp%3A%2F%2Ftracker.openbittorrent.com%3A80","udp%3A%2F%2Fopen.demonii.com%3A1337","udp%3A%2F%2Ftracker.coppersurfer.tk%3A6969","udp%3A%2F%2Fexodus.desync.com%3A6969"],"infoHash":"4aff1f42249b0a4a06c82a87d8790c60310b8f59","infoHashBuffer":{"type":"Buffer","data":[74,255,31,66,36,155,10,74,6,200,42,135,216,121,12,96,49,11,143,89]},"announce":[],"urlList":[]}}