{"title":"Private Magazine 003 RETRO XXX MAG SHAREGO","uid":4416524,"size":3618442,"categoryP":"porn","categoryS":"other","magnet":"?xt=urn:btih:567c60796c229a199ee293e6d7a0097bb1ca8509&amp;dn=Private+Magazine+003+RETRO+XXX+MAG+SHAREGO&amp;tr=udp%3A%2F%2Ftracker.openbittorrent.com%3A80&amp;tr=udp%3A%2F%2Fopen.demonii.com%3A1337&amp;tr=udp%3A%2F%2Ftracker.coppersurfer.tk%3A6969&amp;tr=udp%3A%2F%2Fexodus.desync.com%3A6969","seeders":0,"leechers":2,"uploader":"dodgerblue","files":4,"time":1222544727,"description":"Private Magazine 003 RETRO XXX MAG SHAREGO\nFORMAT 3.45 MB\n[IMG]http://www.tinypic.ws/files/pz0ik75vq7pnc1grjbyv.jpg[/IMG]\n[img]http://images1.filecloud.com/607500/Appriciation.gif[/img]\n","torrent":{"xt":"urn:btih:567c60796c229a199ee293e6d7a0097bb1ca8509","amp;dn":"Private+Magazine+003+RETRO+XXX+MAG+SHAREGO","amp;tr":["udp%3A%2F%2Ftracker.openbittorrent.com%3A80","udp%3A%2F%2Fopen.demonii.com%3A1337","udp%3A%2F%2Ftracker.coppersurfer.tk%3A6969","udp%3A%2F%2Fexodus.desync.com%3A6969"],"infoHash":"567c60796c229a199ee293e6d7a0097bb1ca8509","infoHashBuffer":{"type":"Buffer","data":[86,124,96,121,108,34,154,25,158,226,147,230,215,160,9,123,177,202,133,9]},"announce":[],"urlList":[]}}