{"title":"30.Rock.S05E16.HDTV.XviD-LOL","uid":6200844,"size":183557133,"categoryP":"video","categoryS":"tv_shows","magnet":"?xt=urn:btih:627f637eef7ff0355c036d89cdf4f051e3628b29&amp;dn=30.Rock.S05E16.HDTV.XviD-LOL&amp;tr=udp%3A%2F%2Ftracker.openbittorrent.com%3A80&amp;tr=udp%3A%2F%2Fopen.demonii.com%3A1337&amp;tr=udp%3A%2F%2Ftracker.coppersurfer.tk%3A6969&amp;tr=udp%3A%2F%2Fexodus.desync.com%3A6969","seeders":0,"leechers":1,"uploader":"TvTeam","files":4,"time":1298610212,"description":". \n  &lt;a href=&quot;\nhttp://www.torrentday.com/&quot; rel=&quot;nofollow&quot; target=&quot;_NEW&quot;&gt;\nhttp://www.torrentday.com/&lt;/a&gt;        :     The Hottest Private Tracker On The Net!!!\n\n\nTo Avoid Fakes, ALWAYS Check That The Torrent Was Added By: TvTeam.\n\n\n               www . TorrentDay . Com \n(((((((((((((= Enjoy No RAR releases =))))))))))))))))))))\n\n...................................NFO:....................................\n\n.30 Rock S5 E6teen\n\nHate the dicks, love the CoQ.","torrent":{"xt":"urn:btih:627f637eef7ff0355c036d89cdf4f051e3628b29","amp;dn":"30.Rock.S05E16.HDTV.XviD-LOL","amp;tr":["udp%3A%2F%2Ftracker.openbittorrent.com%3A80","udp%3A%2F%2Fopen.demonii.com%3A1337","udp%3A%2F%2Ftracker.coppersurfer.tk%3A6969","udp%3A%2F%2Fexodus.desync.com%3A6969"],"infoHash":"627f637eef7ff0355c036d89cdf4f051e3628b29","infoHashBuffer":{"type":"Buffer","data":[98,127,99,126,239,127,240,53,92,3,109,137,205,244,240,81,227,98,139,41]},"announce":[],"urlList":[]}}