{"title":"[BIG TITS] Vipersdenforums.com ~ Kelly Prettyman - BigTitsRoundA","uid":3611405,"size":378899416,"categoryP":"porn","categoryS":"movies","magnet":"?xt=urn:btih:7c5d84eaa29dd87cdf7db14882c18d1262dd226e&amp;dn=%5BBIG+TITS%5D+Vipersdenforums.com+%7E+Kelly+Prettyman+-+BigTitsRoundA&amp;tr=udp%3A%2F%2Ftracker.openbittorrent.com%3A80&amp;tr=udp%3A%2F%2Fopen.demonii.com%3A1337&amp;tr=udp%3A%2F%2Ftracker.coppersurfer.tk%3A6969&amp;tr=udp%3A%2F%2Fexodus.desync.com%3A6969","seeders":0,"leechers":0,"uploader":"Shoey1964","files":2,"time":1170634673,"description":"Kelly Prettyman latest hardcore from BigTitsRoundAsses.com\nDirect link preview: &lt;a href=&quot;\nhttp://www.vipersdenforums.com/MATURE/showthread.php?t=326&quot; rel=&quot;nofollow&quot; target=&quot;_NEW&quot;&gt;\nhttp://www.vipersdenforums.com/MATURE/showthread.php?t=326&lt;/a&gt;\nPublic preview: &lt;a href=&quot;\nhttp://img12.imagepile.net/img12/60904thumbs20070205060922.jpg&quot; rel=&quot;nofollow&quot; target=&quot;_NEW&quot;&gt;\nhttp://img12.imagepile.net/img12/60904thumbs20070205060922.jpg&lt;/a&gt;\n\nAll my Pirate Bay torrent shares:\n &lt;a href=&quot;\nhttp://thepiratebay.se/user/Shoey1964/&quot; rel=&quot;nofollow&quot; target=&quot;_NEW&quot;&gt;\nhttp://thepiratebay.se/user/Shoey1964/&lt;/a&gt;","torrent":{"xt":"urn:btih:7c5d84eaa29dd87cdf7db14882c18d1262dd226e","amp;dn":"%5BBIG+TITS%5D+Vipersdenforums.com+%7E+Kelly+Prettyman+-+BigTitsRoundA","amp;tr":["udp%3A%2F%2Ftracker.openbittorrent.com%3A80","udp%3A%2F%2Fopen.demonii.com%3A1337","udp%3A%2F%2Ftracker.coppersurfer.tk%3A6969","udp%3A%2F%2Fexodus.desync.com%3A6969"],"infoHash":"7c5d84eaa29dd87cdf7db14882c18d1262dd226e","infoHashBuffer":{"type":"Buffer","data":[124,93,132,234,162,157,216,124,223,125,177,72,130,193,141,18,98,221,34,110]},"announce":[],"urlList":[]}}