{"title":"Zeitgeist - Moving Forward | 2011 Final - DVDRip/HunSub/Xvid","uid":6208780,"size":1489984552,"categoryP":"video","categoryS":"movies","magnet":"?xt=urn:btih:82ee4d8998eb25995188e296066b05eabe8a27b5&amp;dn=Zeitgeist+-+Moving+Forward+%7C+2011+Final+-+DVDRip%2FHunSub%2FXvid&amp;tr=udp%3A%2F%2Ftracker.openbittorrent.com%3A80&amp;tr=udp%3A%2F%2Fopen.demonii.com%3A1337&amp;tr=udp%3A%2F%2Ftracker.coppersurfer.tk%3A6969&amp;tr=udp%3A%2F%2Fexodus.desync.com%3A6969","seeders":0,"leechers":0,"uploader":"tkslov","files":2,"time":1298905960,"description":"A feature length documentary work which presents a case for a needed transition out of the current socioeconomic monetary paradigm which governs the entire world society. This subject matter will transcend the issues of cultural relativism and traditional ideology and move to relate the core, empirical &quot;life ground&quot; attributes of human and social survival, extrapolating those immutable natural laws into a new sustainable social paradigm called a &quot;Resource-Based Economy&quot;. Written by ArchGunner ","torrent":{"xt":"urn:btih:82ee4d8998eb25995188e296066b05eabe8a27b5","amp;dn":"Zeitgeist+-+Moving+Forward+%7C+2011+Final+-+DVDRip%2FHunSub%2FXvid","amp;tr":["udp%3A%2F%2Ftracker.openbittorrent.com%3A80","udp%3A%2F%2Fopen.demonii.com%3A1337","udp%3A%2F%2Ftracker.coppersurfer.tk%3A6969","udp%3A%2F%2Fexodus.desync.com%3A6969"],"infoHash":"82ee4d8998eb25995188e296066b05eabe8a27b5","infoHashBuffer":{"type":"Buffer","data":[130,238,77,137,152,235,37,153,81,136,226,150,6,107,5,234,190,138,39,181]},"announce":[],"urlList":[]}}