{"title":"Illegal.Tender.2007.DVDRip-Morsan(SweSub)","uid":4669707,"size":735148400,"categoryP":"video","categoryS":"movies","magnet":"?xt=urn:btih:840ea192bf6ee212abed0d8badb774b1a51c872c&amp;dn=Illegal.Tender.2007.DVDRip-Morsan%28SweSub%29&amp;tr=udp%3A%2F%2Ftracker.openbittorrent.com%3A80&amp;tr=udp%3A%2F%2Fopen.demonii.com%3A1337&amp;tr=udp%3A%2F%2Ftracker.coppersurfer.tk%3A6969&amp;tr=udp%3A%2F%2Fexodus.desync.com%3A6969","seeders":0,"leechers":1,"uploader":"truskan","files":-1,"time":1232691508,"description":"Illegal Tender (2007) [Swe HardSub]\n\n\n\nMovie: Illegal Tender (2007)\nhttp://www.imdb.com/title/tt0775488/\nUser Rating: 5.1/10   953 votes\nGenre: Crime | Drama | Thriller\nFiles: 1x699,89 MB\nVideo: XviD 806 KB/s 640 x 272 @25fps\nAudio: MPEG-1 Layer 3 (MP3) 144 KB/s (VBR)\nSource: DVD PAL\nLanguage: English\nSubtitles: Swe (Hardsub)\n\n\nPlot\nWhen the thugs who killed his father come looking \nfor him, a young Latino man and his mother \nflee from their home.\n\n\n\n\nAvi Info\nFile Name ..........: Illegal.Tender.2007.DVDRip-Morsan.avi\nTotal Size (Bytes) .: 733Ã‚Â 890Ã‚Â 560 Bytes\nTotal Size (KB) ....: 716Ã‚Â 690 KB\nTotal Size (MB) ....: 699,89 MB\nTotal Streams ......: 2 Stream(s)\nFile Size Correct ..: Yes\n\nVideo Size (Bytes) .: 622Ã‚Â 680Ã‚Â 944 Bytes\nVideo Size (KB) ....: 608Ã‚Â 087 KB\nVideo Size (MB) ....: 593,83 MB\nVideo Length .......: 01:42:55\nVideo Codec Code ...: XVID\nVideo Codec Name ...: XviD MPEG-4 codec\nVideo Bitrate ......: 806 KB/s\nResolution .........: 640 x 272\nAspect Ratio .......: 2.35:1\nTotal Frames .......: 154366 Frames\nFramerate ..........: 25 FPS\nColor Depth ........: 12 Bits\nQuality Factor .....: 0,185 B/px\nPacked Bitstream ...: Yes\n\nAudio Size (Bytes) .: 111Ã‚Â 199Ã‚Â 400 Bytes\nAudio Size (KB) ....: 108Ã‚Â 593 KB\nAudio Size (MB) ....: 106,05 MB\nAudio Length .......: 01:42:55\nAudio Codec Code ...: 85 (0x0055)\nAudio Codec Name ...: MPEG-1 Layer 3 (MP3)\nAudio Bitrate ......: 144 KB/s (VBR)\nChannels ...........: 2 Ch\nSampling Rate ......: 48000 Hz\n","torrent":{"xt":"urn:btih:840ea192bf6ee212abed0d8badb774b1a51c872c","amp;dn":"Illegal.Tender.2007.DVDRip-Morsan%28SweSub%29","amp;tr":["udp%3A%2F%2Ftracker.openbittorrent.com%3A80","udp%3A%2F%2Fopen.demonii.com%3A1337","udp%3A%2F%2Ftracker.coppersurfer.tk%3A6969","udp%3A%2F%2Fexodus.desync.com%3A6969"],"infoHash":"840ea192bf6ee212abed0d8badb774b1a51c872c","infoHashBuffer":{"type":"Buffer","data":[132,14,161,146,191,110,226,18,171,237,13,139,173,183,116,177,165,28,135,44]},"announce":[],"urlList":[]}}