{"title":"Angels &amp; Demons (2009) R5 LINE DVDR-sailo1","uid":4973837,"size":4631373824,"categoryP":"video","categoryS":"movies_dvdr","magnet":"?xt=urn:btih:93ba9ef44bdf266d2456dbe9edc6a5a0a0682e9d&amp;dn=Angels+%26+Demons+%282009%29+R5+LINE+DVDR-sailo1&amp;tr=udp%3A%2F%2Ftracker.openbittorrent.com%3A80&amp;tr=udp%3A%2F%2Fopen.demonii.com%3A1337&amp;tr=udp%3A%2F%2Ftracker.coppersurfer.tk%3A6969&amp;tr=udp%3A%2F%2Fexodus.desync.com%3A6969","seeders":0,"leechers":0,"uploader":"sailo","files":-1,"time":1245896558,"description":" &lt;a href=&quot;http://www.imdb.com/title/tt0808151/&quot; rel=&quot;nofollow&quot; target=&quot;_NEW&quot;&gt;http://www.imdb.com/title/tt0808151/&lt;/a&gt;\n\n\nAngels And Demons 2009 R5 PAL CUSTOM ROSUB DVDR-iAPULA, with added custom subs.\n\nEnglish  DD2.0-192Kbps\n\nSubs : Romanian , Spanish, Dutch, Portuguese,Danish, Chinese\n","torrent":{"xt":"urn:btih:93ba9ef44bdf266d2456dbe9edc6a5a0a0682e9d","amp;dn":"Angels+%26+Demons+%282009%29+R5+LINE+DVDR-sailo1","amp;tr":["udp%3A%2F%2Ftracker.openbittorrent.com%3A80","udp%3A%2F%2Fopen.demonii.com%3A1337","udp%3A%2F%2Ftracker.coppersurfer.tk%3A6969","udp%3A%2F%2Fexodus.desync.com%3A6969"],"infoHash":"93ba9ef44bdf266d2456dbe9edc6a5a0a0682e9d","infoHashBuffer":{"type":"Buffer","data":[147,186,158,244,75,223,38,109,36,86,219,233,237,198,165,160,160,104,46,157]},"announce":[],"urlList":[]}}