{"title":"virtualdj","uid":3550478,"size":40077583,"categoryP":"applications","categoryS":"windows","magnet":"?xt=urn:btih:97bd0fb98a79f17e88af9053eb1b353294b77cf0&amp;dn=virtualdj&amp;tr=udp%3A%2F%2Ftracker.openbittorrent.com%3A80&amp;tr=udp%3A%2F%2Fopen.demonii.com%3A1337&amp;tr=udp%3A%2F%2Ftracker.coppersurfer.tk%3A6969&amp;tr=udp%3A%2F%2Fexodus.desync.com%3A6969","seeders":0,"leechers":0,"uploader":"loongti","files":3,"time":1162537908,"description":"Welcome to VirtualDJ, the DJ software that is at the same time\nthe easiest and the most powerful on the market.\n\nEasiest: fit with an evolutionary interface engine, the look and feel of VirtualDJ adapts itself to your level. Start with an easy-to-use skin to learn with, then choose amongst the dozen skins available on this website, from the simplest to the most complex ones.\n\nPowerful: VirtualDJ is today\\&amp;#039;s only software to provide:\n- A clear superimposed view of the music beats\n- A synchronized sampler for intuitive live remixes\n- Music video scratching, with an unrivalled fluidity\n- An anti-skip technology, when scratching with timecoded vinyls\n- And many other extraordinary features as you\\&amp;#039;ll soon discover...\n\nDo not hesitate any more, there\\&amp;#039;s a reason why VirtualDJ has been adopted by more than 4.000.000 users in the world, making it the most used DJ software on the market.\n","torrent":{"xt":"urn:btih:97bd0fb98a79f17e88af9053eb1b353294b77cf0","amp;dn":"virtualdj","amp;tr":["udp%3A%2F%2Ftracker.openbittorrent.com%3A80","udp%3A%2F%2Fopen.demonii.com%3A1337","udp%3A%2F%2Ftracker.coppersurfer.tk%3A6969","udp%3A%2F%2Fexodus.desync.com%3A6969"],"infoHash":"97bd0fb98a79f17e88af9053eb1b353294b77cf0","infoHashBuffer":{"type":"Buffer","data":[151,189,15,185,138,121,241,126,136,175,144,83,235,27,53,50,148,183,124,240]},"announce":[],"urlList":[]}}