{"title":"SonicOutlaws.mpg","uid":3709705,"size":912785860,"categoryP":"video","categoryS":"movies","magnet":"?xt=urn:btih:998e0dc2599549acc4ad1c424c0dcc770abec0d5&amp;dn=SonicOutlaws.mpg&amp;tr=udp%3A%2F%2Ftracker.openbittorrent.com%3A80&amp;tr=udp%3A%2F%2Fopen.demonii.com%3A1337&amp;tr=udp%3A%2F%2Ftracker.coppersurfer.tk%3A6969&amp;tr=udp%3A%2F%2Fexodus.desync.com%3A6969","seeders":0,"leechers":0,"uploader":"419","files":1,"time":1181434692,"description":"Combining five formats, including FisherPrice Pixelvision, this is a great film on the legal and ethical issues that surround the work of such groups as Negativland, EBN, the Tape Beatles, and John Oswald. It follows the issues raised by Negativland&amp;#039;s infamous single &quot;U2&quot; and is of a format (musically and visually) that one would expect from people who have a collage aesthetic in creating art to comment on the media...","torrent":{"xt":"urn:btih:998e0dc2599549acc4ad1c424c0dcc770abec0d5","amp;dn":"SonicOutlaws.mpg","amp;tr":["udp%3A%2F%2Ftracker.openbittorrent.com%3A80","udp%3A%2F%2Fopen.demonii.com%3A1337","udp%3A%2F%2Ftracker.coppersurfer.tk%3A6969","udp%3A%2F%2Fexodus.desync.com%3A6969"],"infoHash":"998e0dc2599549acc4ad1c424c0dcc770abec0d5","infoHashBuffer":{"type":"Buffer","data":[153,142,13,194,89,149,73,172,196,173,28,66,76,13,204,119,10,190,192,213]},"announce":[],"urlList":[]}}