{"title":"Prison Break 4x13","uid":4553994,"size":366751744,"categoryP":"video","categoryS":"tv_shows","magnet":"?xt=urn:btih:9c0a3cb7a362c0cd4971825577ed6c6eb38cb6de&amp;dn=Prison+Break+4x13&amp;tr=udp%3A%2F%2Ftracker.openbittorrent.com%3A80&amp;tr=udp%3A%2F%2Fopen.demonii.com%3A1337&amp;tr=udp%3A%2F%2Ftracker.coppersurfer.tk%3A6969&amp;tr=udp%3A%2F%2Fexodus.desync.com%3A6969","seeders":0,"leechers":0,"uploader":"XSamX1","files":1,"time":1228412021,"description":"Prison Break 4x13","torrent":{"xt":"urn:btih:9c0a3cb7a362c0cd4971825577ed6c6eb38cb6de","amp;dn":"Prison+Break+4x13","amp;tr":["udp%3A%2F%2Ftracker.openbittorrent.com%3A80","udp%3A%2F%2Fopen.demonii.com%3A1337","udp%3A%2F%2Ftracker.coppersurfer.tk%3A6969","udp%3A%2F%2Fexodus.desync.com%3A6969"],"infoHash":"9c0a3cb7a362c0cd4971825577ed6c6eb38cb6de","infoHashBuffer":{"type":"Buffer","data":[156,10,60,183,163,98,192,205,73,113,130,85,119,237,108,110,179,140,182,222]},"announce":[],"urlList":[]}}