{"title":"Sobrenatural.3x02.[TodoSeries.lospereira.es].avi","uid":4466190,"size":365996032,"categoryP":"video","categoryS":"tv_shows","magnet":"?xt=urn:btih:a23c76c2fd33e96f7ee0a85ecc09314737cf03ea&amp;dn=Sobrenatural.3x02.%5BTodoSeries.lospereira.es%5D.avi&amp;tr=udp%3A%2F%2Ftracker.openbittorrent.com%3A80&amp;tr=udp%3A%2F%2Fopen.demonii.com%3A1337&amp;tr=udp%3A%2F%2Ftracker.coppersurfer.tk%3A6969&amp;tr=udp%3A%2F%2Fexodus.desync.com%3A6969","seeders":0,"leechers":1,"uploader":"lospereira","files":1,"time":1224921197,"description":"Sobrenatural 3x2","torrent":{"xt":"urn:btih:a23c76c2fd33e96f7ee0a85ecc09314737cf03ea","amp;dn":"Sobrenatural.3x02.%5BTodoSeries.lospereira.es%5D.avi","amp;tr":["udp%3A%2F%2Ftracker.openbittorrent.com%3A80","udp%3A%2F%2Fopen.demonii.com%3A1337","udp%3A%2F%2Ftracker.coppersurfer.tk%3A6969","udp%3A%2F%2Fexodus.desync.com%3A6969"],"infoHash":"a23c76c2fd33e96f7ee0a85ecc09314737cf03ea","infoHashBuffer":{"type":"Buffer","data":[162,60,118,194,253,51,233,111,126,224,168,94,204,9,49,71,55,207,3,234]},"announce":[],"urlList":[]}}