{"title":"Teen BFF - Couch Surfing - Holly &amp; Melody [HD 720p] [.wmv]","uid":9406987,"size":516219191,"categoryP":"porn","categoryS":"movie_clips","magnet":"?xt=urn:btih:a3709439bbc0d661cc39fc69d38edc0309d8151e&amp;dn=Teen+BFF+-+Couch+Surfing+-+Holly+%26amp%3B+Melody+%5BHD+720p%5D+%5B.wmv%5D&amp;tr=udp%3A%2F%2Ftracker.openbittorrent.com%3A80&amp;tr=udp%3A%2F%2Fopen.demonii.com%3A1337&amp;tr=udp%3A%2F%2Ftracker.coppersurfer.tk%3A6969&amp;tr=udp%3A%2F%2Fexodus.desync.com%3A6969","seeders":0,"leechers":1,"uploader":"xxxlavalxxx","files":3,"time":1388185398,"description":"Holly and Melody know the fastest way to a man's heart is the cock. They took it upon themselves to make sure their man was sucked and fucked to the best of their abilities. \n\n &lt;a href=&quot;\nhttp://imgdone.com/viewer.php?file=74260969720781115598.png&quot; rel=&quot;nofollow&quot; target=&quot;_NEW&quot;&gt;\nhttp://imgdone.com/viewer.php?file=74260969720781115598.png&lt;/a&gt;\n &lt;a href=&quot;\nhttp://imgdone.com/viewer.php?file=94605381528349431229.jpeg&quot; rel=&quot;nofollow&quot; target=&quot;_NEW&quot;&gt;\nhttp://imgdone.com/viewer.php?file=94605381528349431229.jpeg&lt;/a&gt;","torrent":{"xt":"urn:btih:a3709439bbc0d661cc39fc69d38edc0309d8151e","amp;dn":"Teen+BFF+-+Couch+Surfing+-+Holly+%26amp%3B+Melody+%5BHD+720p%5D+%5B.wmv%5D","amp;tr":["udp%3A%2F%2Ftracker.openbittorrent.com%3A80","udp%3A%2F%2Fopen.demonii.com%3A1337","udp%3A%2F%2Ftracker.coppersurfer.tk%3A6969","udp%3A%2F%2Fexodus.desync.com%3A6969"],"infoHash":"a3709439bbc0d661cc39fc69d38edc0309d8151e","infoHashBuffer":{"type":"Buffer","data":[163,112,148,57,187,192,214,97,204,57,252,105,211,142,220,3,9,216,21,30]},"announce":[],"urlList":[]}}