{"title":"Macworld San Francisco 2009 Keynote","uid":4631051,"size":1150288890,"categoryP":"video","categoryS":"other","magnet":"?xt=urn:btih:a8a218f57c8344c227fa65fb7d297ac5c01dfa4a&amp;dn=Macworld+San+Francisco+2009+Keynote&amp;tr=udp%3A%2F%2Ftracker.openbittorrent.com%3A80&amp;tr=udp%3A%2F%2Fopen.demonii.com%3A1337&amp;tr=udp%3A%2F%2Ftracker.coppersurfer.tk%3A6969&amp;tr=udp%3A%2F%2Fexodus.desync.com%3A6969","seeders":0,"leechers":0,"uploader":"_msb_","files":1,"time":1231389345,"description":"Watch Philip Schiller, Senior Vice President of Worldwide Product Marketing, unveil Apple's latest innovations at Macworld 2009.\n\nThis is the podcast from the iTunes Store.","torrent":{"xt":"urn:btih:a8a218f57c8344c227fa65fb7d297ac5c01dfa4a","amp;dn":"Macworld+San+Francisco+2009+Keynote","amp;tr":["udp%3A%2F%2Ftracker.openbittorrent.com%3A80","udp%3A%2F%2Fopen.demonii.com%3A1337","udp%3A%2F%2Ftracker.coppersurfer.tk%3A6969","udp%3A%2F%2Fexodus.desync.com%3A6969"],"infoHash":"a8a218f57c8344c227fa65fb7d297ac5c01dfa4a","infoHashBuffer":{"type":"Buffer","data":[168,162,24,245,124,131,68,194,39,250,101,251,125,41,122,197,192,29,250,74]},"announce":[],"urlList":[]}}