{"title":"Model-eve - set 10","uid":5442315,"size":38854913,"categoryP":"porn","categoryS":"pictures","magnet":"?xt=urn:btih:a99b4aea5a80fc70e5fe907c3a8612375a74f905&amp;dn=Model-eve+-+set+10&amp;tr=udp%3A%2F%2Ftracker.openbittorrent.com%3A80&amp;tr=udp%3A%2F%2Fopen.demonii.com%3A1337&amp;tr=udp%3A%2F%2Ftracker.coppersurfer.tk%3A6969&amp;tr=udp%3A%2F%2Fexodus.desync.com%3A6969","seeders":0,"leechers":1,"uploader":"vmackey","files":135,"time":1268918597,"description":"Model-eve - set 10 from model-eve.com\n\nPreview:\n &lt;a href=&quot;\nhttp://galleryhosted.com/?v=652034772.jpg&quot; rel=&quot;nofollow&quot; target=&quot;_NEW&quot;&gt;\nhttp://galleryhosted.com/?v=652034772.jpg&lt;/a&gt;","torrent":{"xt":"urn:btih:a99b4aea5a80fc70e5fe907c3a8612375a74f905","amp;dn":"Model-eve+-+set+10","amp;tr":["udp%3A%2F%2Ftracker.openbittorrent.com%3A80","udp%3A%2F%2Fopen.demonii.com%3A1337","udp%3A%2F%2Ftracker.coppersurfer.tk%3A6969","udp%3A%2F%2Fexodus.desync.com%3A6969"],"infoHash":"a99b4aea5a80fc70e5fe907c3a8612375a74f905","infoHashBuffer":{"type":"Buffer","data":[169,155,74,234,90,128,252,112,229,254,144,124,58,134,18,55,90,116,249,5]},"announce":[],"urlList":[]}}