{"title":"The Metal Years 1978-1983","uid":3706893,"size":66626648,"categoryP":"audio","categoryS":"music","magnet":"?xt=urn:btih:af093e3cb22f010f635c70e4b8ec835ea976293b&amp;dn=The+Metal+Years+1978-1983&amp;tr=udp%3A%2F%2Ftracker.openbittorrent.com%3A80&amp;tr=udp%3A%2F%2Fopen.demonii.com%3A1337&amp;tr=udp%3A%2F%2Ftracker.coppersurfer.tk%3A6969&amp;tr=udp%3A%2F%2Fexodus.desync.com%3A6969","seeders":0,"leechers":1,"uploader":"neepy","files":20,"time":1181127800,"description":"Iron Maiden\n\nThe Metal Years 1978-1983\n\n1 Iron Maiden\n2 Invasion\n3 Prowler\n4 Iron Maiden\n5 Running Free\n6 Transylvania\n7 Sanctuary\n8 Women In Uniform\n9 Ive Got The Fire\n10 Twilight Zone\n11 Wrathchild\n12 Killers\n13 The Trooper\n14 Revelations\n15 Flight Of Icarus\n16 22 Acacia Avenue\n17 The Number Of The Beast\n\n\nArtwork Included\n\nTracks 1-3\n3 Track Demo Recorded At The Spaceward Studios,Cambridge,UK\nOn Dec 30th 1978 And Subsequently Issued As A Strictly Limited\n7\\&quot; Edition The Soundhouse Tapes\n\nTracks 4-7\nBBC Sessions,London,UK Dec 14th 1979\n\nTracks 8-9\nTop Of The Pops,London,UK Feb 10th 1980\n\nTracks 10-12\nFirst Demo Tape With Bruce Dickinson,London,UK Sept 1981\n\nTracks 13-17\nH.M For Xmas Festival,Dortmund,Germany Dec 18th 1983\n\nCome And Join us at http://madonmaiden.proboards83.com/index.cgi\nFor Loads More Maiden Audio/Video Boots\n","torrent":{"xt":"urn:btih:af093e3cb22f010f635c70e4b8ec835ea976293b","amp;dn":"The+Metal+Years+1978-1983","amp;tr":["udp%3A%2F%2Ftracker.openbittorrent.com%3A80","udp%3A%2F%2Fopen.demonii.com%3A1337","udp%3A%2F%2Ftracker.coppersurfer.tk%3A6969","udp%3A%2F%2Fexodus.desync.com%3A6969"],"infoHash":"af093e3cb22f010f635c70e4b8ec835ea976293b","infoHashBuffer":{"type":"Buffer","data":[175,9,62,60,178,47,1,15,99,92,112,228,184,236,131,94,169,118,41,59]},"announce":[],"urlList":[]}}