{"title":"The Invaders Season 2 Ep. 3 - The Watchers","uid":11635726,"size":595946057,"categoryP":"video","categoryS":"tv_shows","magnet":"?xt=urn:btih:b3fa52d4152184d9860428a783eb71bc58bfe455&amp;dn=The+Invaders+Season+2+Ep.+3+-+The+Watchers&amp;tr=udp%3A%2F%2Ftracker.openbittorrent.com%3A80&amp;tr=udp%3A%2F%2Fopen.demonii.com%3A1337&amp;tr=udp%3A%2F%2Ftracker.coppersurfer.tk%3A6969&amp;tr=udp%3A%2F%2Fexodus.desync.com%3A6969","seeders":0,"leechers":0,"uploader":"Mooseleg8","files":-1,"time":1417731447,"description":"Paul Cook is an electronics genius with an aversion to people. He is also the man several generals are coming to meet, because he can analyze the nation's defenses and suggest ways to correct their flaws. But beings from an alien would would also like a look at those defenses, and they have devised a plan that takes advantage of Cook's reclusive nature. If David Vincent cannot stop them, they will get that information, and use it to advance their invasion timetable!","torrent":{"xt":"urn:btih:b3fa52d4152184d9860428a783eb71bc58bfe455","amp;dn":"The+Invaders+Season+2+Ep.+3+-+The+Watchers","amp;tr":["udp%3A%2F%2Ftracker.openbittorrent.com%3A80","udp%3A%2F%2Fopen.demonii.com%3A1337","udp%3A%2F%2Ftracker.coppersurfer.tk%3A6969","udp%3A%2F%2Fexodus.desync.com%3A6969"],"infoHash":"b3fa52d4152184d9860428a783eb71bc58bfe455","infoHashBuffer":{"type":"Buffer","data":[179,250,82,212,21,33,132,217,134,4,40,167,131,235,113,188,88,191,228,85]},"announce":[],"urlList":[]}}