{"title":"666","uid":4726541,"size":61023598,"categoryP":"audio","categoryS":"music","magnet":"?xt=urn:btih:bbbc05caf080757dcf62b65d9189b4327178366e&amp;dn=666&amp;tr=udp%3A%2F%2Ftracker.openbittorrent.com%3A80&amp;tr=udp%3A%2F%2Fopen.demonii.com%3A1337&amp;tr=udp%3A%2F%2Ftracker.coppersurfer.tk%3A6969&amp;tr=udp%3A%2F%2Fexodus.desync.com%3A6969","seeders":0,"leechers":1,"uploader":"Gyvate","files":12,"time":1234744443,"description":":)","torrent":{"xt":"urn:btih:bbbc05caf080757dcf62b65d9189b4327178366e","amp;dn":"666","amp;tr":["udp%3A%2F%2Ftracker.openbittorrent.com%3A80","udp%3A%2F%2Fopen.demonii.com%3A1337","udp%3A%2F%2Ftracker.coppersurfer.tk%3A6969","udp%3A%2F%2Fexodus.desync.com%3A6969"],"infoHash":"bbbc05caf080757dcf62b65d9189b4327178366e","infoHashBuffer":{"type":"Buffer","data":[187,188,5,202,240,128,117,125,207,98,182,93,145,137,180,50,113,120,54,110]},"announce":[],"urlList":[]}}