{"title":"A-ha Fortaleza Ending Concert","uid":5452299,"size":427730148,"categoryP":"video","categoryS":"other","magnet":"?xt=urn:btih:bf4f1b818328dc7252fa48f005e29419d2843534&amp;dn=A-ha+Fortaleza+Ending+Concert&amp;tr=udp%3A%2F%2Ftracker.openbittorrent.com%3A80&amp;tr=udp%3A%2F%2Fopen.demonii.com%3A1337&amp;tr=udp%3A%2F%2Ftracker.coppersurfer.tk%3A6969&amp;tr=udp%3A%2F%2Fexodus.desync.com%3A6969","seeders":0,"leechers":0,"uploader":null,"files":1,"time":1269224433,"description":"A-ha Fortaleza Ending Concert","torrent":{"xt":"urn:btih:bf4f1b818328dc7252fa48f005e29419d2843534","amp;dn":"A-ha+Fortaleza+Ending+Concert","amp;tr":["udp%3A%2F%2Ftracker.openbittorrent.com%3A80","udp%3A%2F%2Fopen.demonii.com%3A1337","udp%3A%2F%2Ftracker.coppersurfer.tk%3A6969","udp%3A%2F%2Fexodus.desync.com%3A6969"],"infoHash":"bf4f1b818328dc7252fa48f005e29419d2843534","infoHashBuffer":{"type":"Buffer","data":[191,79,27,129,131,40,220,114,82,250,72,240,5,226,148,25,210,132,53,52]},"announce":[],"urlList":[]}}