{"title":"[MilfsLikeItBlack.com / Mofos.com] Austin Taylor","uid":6097675,"size":1957131372,"categoryP":"porn","categoryS":"movies","magnet":"?xt=urn:btih:c2447e47ca9bec0cbadd90758433d0d32da61dd4&amp;dn=%5BMilfsLikeItBlack.com+%2F+Mofos.com%5D+Austin+Taylor&amp;tr=udp%3A%2F%2Ftracker.openbittorrent.com%3A80&amp;tr=udp%3A%2F%2Fopen.demonii.com%3A1337&amp;tr=udp%3A%2F%2Ftracker.coppersurfer.tk%3A6969&amp;tr=udp%3A%2F%2Fexodus.desync.com%3A6969","seeders":0,"leechers":0,"uploader":"exmnova","files":1,"time":1294842626,"description":"[MilfsLikeItBlack.com / Mofos.com] Austin Taylor\n\n\n","torrent":{"xt":"urn:btih:c2447e47ca9bec0cbadd90758433d0d32da61dd4","amp;dn":"%5BMilfsLikeItBlack.com+%2F+Mofos.com%5D+Austin+Taylor","amp;tr":["udp%3A%2F%2Ftracker.openbittorrent.com%3A80","udp%3A%2F%2Fopen.demonii.com%3A1337","udp%3A%2F%2Ftracker.coppersurfer.tk%3A6969","udp%3A%2F%2Fexodus.desync.com%3A6969"],"infoHash":"c2447e47ca9bec0cbadd90758433d0d32da61dd4","infoHashBuffer":{"type":"Buffer","data":[194,68,126,71,202,155,236,12,186,221,144,117,132,51,208,211,45,166,29,212]},"announce":[],"urlList":[]}}