{"title":"Kiss.Of.The.Vampire.1963.BRRip.XviD.MP3-RARBG","uid":11626509,"size":1196347626,"categoryP":"video","categoryS":"movies","magnet":"?xt=urn:btih:c290ddd8ab461b69f2026362e876a042745709c2&amp;dn=Kiss.Of.The.Vampire.1963.BRRip.XviD.MP3-RARBG&amp;tr=udp%3A%2F%2Ftracker.openbittorrent.com%3A80&amp;tr=udp%3A%2F%2Fopen.demonii.com%3A1337&amp;tr=udp%3A%2F%2Ftracker.coppersurfer.tk%3A6969&amp;tr=udp%3A%2F%2Fexodus.desync.com%3A6969","seeders":0,"leechers":2,"uploader":"Drarbg","files":5,"time":1417627811,"description":" &lt;a href=&quot;https://rarbg.com&quot; rel=&quot;nofollow&quot; target=&quot;_NEW&quot;&gt;https://rarbg.com&lt;/a&gt;\n\nKiss.Of.The.Vampire.1963.BRRip.XviD.MP3-RARBG\n\nAuto IMDB: &lt;a href=&quot;\nhttp://www.imdb.com/title/tt0066518/&quot; rel=&quot;nofollow&quot; target=&quot;_NEW&quot;&gt;\nhttp://www.imdb.com/title/tt0066518/&lt;/a&gt;\n\n-----------------------------------------\nScreens : &lt;a href=&quot;\nhttp://imgcrl.org/v/13592839898271029446/&quot; rel=&quot;nofollow&quot; target=&quot;_NEW&quot;&gt;\nhttp://imgcrl.org/v/13592839898271029446/&lt;/a&gt; &lt;a href=&quot;\nhttp://imgcrl.org/v/43390402394222967283/&quot; rel=&quot;nofollow&quot; target=&quot;_NEW&quot;&gt;\nhttp://imgcrl.org/v/43390402394222967283/&lt;/a&gt; &lt;a href=&quot;\nhttp://imgcrl.org/v/05382060016388392069/&quot; rel=&quot;nofollow&quot; target=&quot;_NEW&quot;&gt;\nhttp://imgcrl.org/v/05382060016388392069/&lt;/a&gt; &lt;a href=&quot;\nhttp://imgcrl.org/v/97015225027910346019/&quot; rel=&quot;nofollow&quot; target=&quot;_NEW&quot;&gt;\nhttp://imgcrl.org/v/97015225027910346019/&lt;/a&gt; &lt;a href=&quot;\nhttp://imgcrl.org/v/79364815713194449268/&quot; rel=&quot;nofollow&quot; target=&quot;_NEW&quot;&gt;\nhttp://imgcrl.org/v/79364815713194449268/&lt;/a&gt;\n\n-----------------------------------------\nAuto Media Info :\nVideo Format........: MPEG-4 Visual\nCodec ID............: XVID\nCodec ID/Hint.......: XviD\nLength..............: 1h28mn\nVideo...............: 720x392 ( 23.976fps )\nBitrate.............: 1600Kbps\nAudio Format........: MPEG Audio\nCodec ID............: 55\nCodec ID/Hint.......: MP3\nBit rate mode.......: Constant\nBitrate.............: 192Kbps\nChannel(s)..........: 2 channels","torrent":{"xt":"urn:btih:c290ddd8ab461b69f2026362e876a042745709c2","amp;dn":"Kiss.Of.The.Vampire.1963.BRRip.XviD.MP3-RARBG","amp;tr":["udp%3A%2F%2Ftracker.openbittorrent.com%3A80","udp%3A%2F%2Fopen.demonii.com%3A1337","udp%3A%2F%2Ftracker.coppersurfer.tk%3A6969","udp%3A%2F%2Fexodus.desync.com%3A6969"],"infoHash":"c290ddd8ab461b69f2026362e876a042745709c2","infoHashBuffer":{"type":"Buffer","data":[194,144,221,216,171,70,27,105,242,2,99,98,232,118,160,66,116,87,9,194]},"announce":[],"urlList":[]}}