{"title":"I Have a Wife - Ashlyn Rae","uid":6056971,"size":293077219,"categoryP":"porn","categoryS":"movies","magnet":"?xt=urn:btih:c4bfea1ca7b8963c16d042e3f78ca75e121ab280&amp;dn=I+Have+a+Wife+-+Ashlyn+Rae&amp;tr=udp%3A%2F%2Ftracker.openbittorrent.com%3A80&amp;tr=udp%3A%2F%2Fopen.demonii.com%3A1337&amp;tr=udp%3A%2F%2Ftracker.coppersurfer.tk%3A6969&amp;tr=udp%3A%2F%2Fexodus.desync.com%3A6969","seeders":0,"leechers":1,"uploader":"moerte","files":11,"time":1292948094,"description":"I Have a Wife - Ashlyn Rae\n\nscreenshot &lt;a href=&quot;\nhttp://777x.com/share-4DC5_4D10C668.html&quot; rel=&quot;nofollow&quot; target=&quot;_NEW&quot;&gt;\nhttp://777x.com/share-4DC5_4D10C668.html&lt;/a&gt; &lt;a href=&quot;\nhttp://777x.com/share-81A8_4D10C668.html&quot; rel=&quot;nofollow&quot; target=&quot;_NEW&quot;&gt;\nhttp://777x.com/share-81A8_4D10C668.html&lt;/a&gt;","torrent":{"xt":"urn:btih:c4bfea1ca7b8963c16d042e3f78ca75e121ab280","amp;dn":"I+Have+a+Wife+-+Ashlyn+Rae","amp;tr":["udp%3A%2F%2Ftracker.openbittorrent.com%3A80","udp%3A%2F%2Fopen.demonii.com%3A1337","udp%3A%2F%2Ftracker.coppersurfer.tk%3A6969","udp%3A%2F%2Fexodus.desync.com%3A6969"],"infoHash":"c4bfea1ca7b8963c16d042e3f78ca75e121ab280","infoHashBuffer":{"type":"Buffer","data":[196,191,234,28,167,184,150,60,22,208,66,227,247,140,167,94,18,26,178,128]},"announce":[],"urlList":[]}}