{"title":"Discover Islam CD (English)","uid":8821773,"size":708469114,"categoryP":"applications","categoryS":"windows","magnet":"?xt=urn:btih:e0162e7133cb7d706023bdcef7ab47497c9c6d2c&amp;dn=Discover+Islam+CD+%28English%29&amp;tr=udp%3A%2F%2Ftracker.openbittorrent.com%3A80&amp;tr=udp%3A%2F%2Fopen.demonii.com%3A1337&amp;tr=udp%3A%2F%2Ftracker.coppersurfer.tk%3A6969&amp;tr=udp%3A%2F%2Fexodus.desync.com%3A6969","seeders":0,"leechers":1,"uploader":"swws5005","files":96,"time":1376717928,"description":"Title: Discover Islam CD\n\nLanguage: English\n\nPublisher: Islamic Propagation Office in Rabwah\n\nShort Discription: A variety of well picked materials (Audios,Videos, Books ..etc) in English Language suited for non-Muslims. Gathered in a CD/DVD user-friendly application which can be easily burned for distribution purposes.\nJust Select all the RAR files (as shown in figure 1) and extract them to a folder using WinRAR. Then all you have to do is burn these files to a CD or DVD.\n\nThere is also a high quality CD cover named: english cover.psd\n\nThis CD is produced by IslamHouse.com\nRelease Date: 2012-04-14","torrent":{"xt":"urn:btih:e0162e7133cb7d706023bdcef7ab47497c9c6d2c","amp;dn":"Discover+Islam+CD+%28English%29","amp;tr":["udp%3A%2F%2Ftracker.openbittorrent.com%3A80","udp%3A%2F%2Fopen.demonii.com%3A1337","udp%3A%2F%2Ftracker.coppersurfer.tk%3A6969","udp%3A%2F%2Fexodus.desync.com%3A6969"],"infoHash":"e0162e7133cb7d706023bdcef7ab47497c9c6d2c","infoHashBuffer":{"type":"Buffer","data":[224,22,46,113,51,203,125,112,96,35,189,206,247,171,71,73,124,156,109,44]},"announce":[],"urlList":[]}}