{"title":"The secret of the thirteen crystal skulls.","uid":4332555,"size":70898425,"categoryP":"audio","categoryS":"music","magnet":"?xt=urn:btih:e1b30d93905e6d67129a5808fed6f837a1a3a56f&amp;dn=The+secret+of+the+thirteen+crystal+skulls.&amp;tr=udp%3A%2F%2Ftracker.openbittorrent.com%3A80&amp;tr=udp%3A%2F%2Fopen.demonii.com%3A1337&amp;tr=udp%3A%2F%2Ftracker.coppersurfer.tk%3A6969&amp;tr=udp%3A%2F%2Fexodus.desync.com%3A6969","seeders":0,"leechers":1,"uploader":"DjRoflBBQ","files":7,"time":1218126913,"description":"1  \tEat Static   \tThe First Revelation (10:47)\n  \t\n2 \tCyberbabas \tThe Second Revelation (9:34)\n  \t  \n3 \tAlien Project   The The Third Revelation (9:45)\n  \t\n4 \tAstrix \t        The Fourth Revelation (9:30)\n  \t  \n5 \tTalamasca \tThe Fifth Revelation (9:56)\n  \t \n6 \t1200 Mics \tThe Sixth Revelation (10:01)  \t  \n \n7 \tShpongle \tThe Seventh Revelation (14:24)\n","torrent":{"xt":"urn:btih:e1b30d93905e6d67129a5808fed6f837a1a3a56f","amp;dn":"The+secret+of+the+thirteen+crystal+skulls.","amp;tr":["udp%3A%2F%2Ftracker.openbittorrent.com%3A80","udp%3A%2F%2Fopen.demonii.com%3A1337","udp%3A%2F%2Ftracker.coppersurfer.tk%3A6969","udp%3A%2F%2Fexodus.desync.com%3A6969"],"infoHash":"e1b30d93905e6d67129a5808fed6f837a1a3a56f","infoHashBuffer":{"type":"Buffer","data":[225,179,13,147,144,94,109,103,18,154,88,8,254,214,248,55,161,163,165,111]},"announce":[],"urlList":[]}}