{"title":"Luke Meadows House Selection Volume 17","uid":4415243,"size":94754877,"categoryP":"audio","categoryS":"music","magnet":"?xt=urn:btih:e2a1d4f407e53ea91eedfa06286bc658036fac88&amp;dn=Luke+Meadows+House+Selection+Volume+17&amp;tr=udp%3A%2F%2Ftracker.openbittorrent.com%3A80&amp;tr=udp%3A%2F%2Fopen.demonii.com%3A1337&amp;tr=udp%3A%2F%2Ftracker.coppersurfer.tk%3A6969&amp;tr=udp%3A%2F%2Fexodus.desync.com%3A6969","seeders":0,"leechers":1,"uploader":"ConstantDJ","files":1,"time":1222476888,"description":"Luke Meadows House Selection Volume 17\n\n\nTracklist:-\n\n1)  Finally - Kings Of Tomorrow (Extended Orginal Mix)\n2)  Wondrous - Danny Clark &amp; Jay Benham feat Susu\n3)  In Da Club (Shake Sh*t Up) - Copyright feat Mr V &amp; Miss Patty (Chocolate Puma Club Mix)\n4)  Let It Go - Dirty South feat Rudy (Chocolate Puma Vocal Mix)\n5)  Been A Long Time - TV Rock feat Rudy (Laidback Luke Remix)\n6)  Lola's Theme - The Shapeshifters (2008 Re-Edit)\n7)  Coca Loca - Dino Lenny (Bart B More Remix)\n8)  Same Man - Till West &amp; DJ Delicious\n9)  Handsome - Bart Skills &amp; Anton Pieete aka District One\n10) Everybody Be Somebody - Ruffneck feat Yavahn (Acapella)\n11) The Sound Is Yours - Risksoundsystem (Kerri Chandler Remix)\n12) Man With The Red Face - Funkagenda &amp; Mark Knight\n13) Greece 2000 - Three Drives (D.O.N.S &amp; DBN Remix)\n\nYou Can Listen To The Luke Meadows Radio Show Every Tuesday \n8pm-10pm (UK Time) On http://www.unknownfm.net - (Select Listen Live)","torrent":{"xt":"urn:btih:e2a1d4f407e53ea91eedfa06286bc658036fac88","amp;dn":"Luke+Meadows+House+Selection+Volume+17","amp;tr":["udp%3A%2F%2Ftracker.openbittorrent.com%3A80","udp%3A%2F%2Fopen.demonii.com%3A1337","udp%3A%2F%2Ftracker.coppersurfer.tk%3A6969","udp%3A%2F%2Fexodus.desync.com%3A6969"],"infoHash":"e2a1d4f407e53ea91eedfa06286bc658036fac88","infoHashBuffer":{"type":"Buffer","data":[226,161,212,244,7,229,62,169,30,237,250,6,40,107,198,88,3,111,172,136]},"announce":[],"urlList":[]}}