{"title":"Grand Theft Auto III Original Soundtracks (MP3)","uid":8420876,"size":52032954,"categoryP":"audio","categoryS":"music","magnet":"?xt=urn:btih:f26ca5b9653ad9af93c9c48c468630d186c0be95&amp;dn=Grand+Theft+Auto+III+Original+Soundtracks+%28MP3%29&amp;tr=udp%3A%2F%2Ftracker.openbittorrent.com%3A80&amp;tr=udp%3A%2F%2Fopen.demonii.com%3A1337&amp;tr=udp%3A%2F%2Ftracker.coppersurfer.tk%3A6969&amp;tr=udp%3A%2F%2Fexodus.desync.com%3A6969","seeders":0,"leechers":0,"uploader":null,"files":-1,"time":1367187733,"description":"Article/Blog about this original soundtracks bundle:\n  &lt;a href=&quot;\nhttp://www.rockstargames.com/newswire/article/19761/grand-theft-auto-iii-head-radio-lips-fm-station-albums-now-avail.html&quot; rel=&quot;nofollow&quot; target=&quot;_NEW&quot;&gt;\nhttp://www.rockstargames.com/newswire/article/19761/grand-theft-auto-iii-head-radio-lips-fm-station-albums-now-avail.html&lt;/a&gt;\n\n\n---------------------\n\n\nThis bundle contains all of the GTA III songs that were released by Rockstar North, on Dec. 7, 2011. These songs are remixed versions by Rockstar North themselves. \n\nNo commercials, no chatters, just you and the music. Enjoy.\n\nAll files are in MPEG-3 format.","torrent":{"xt":"urn:btih:f26ca5b9653ad9af93c9c48c468630d186c0be95","amp;dn":"Grand+Theft+Auto+III+Original+Soundtracks+%28MP3%29","amp;tr":["udp%3A%2F%2Ftracker.openbittorrent.com%3A80","udp%3A%2F%2Fopen.demonii.com%3A1337","udp%3A%2F%2Ftracker.coppersurfer.tk%3A6969","udp%3A%2F%2Fexodus.desync.com%3A6969"],"infoHash":"f26ca5b9653ad9af93c9c48c468630d186c0be95","infoHashBuffer":{"type":"Buffer","data":[242,108,165,185,101,58,217,175,147,201,196,140,70,134,48,209,134,192,190,149]},"announce":[],"urlList":[]}}